[
  {
    "city": "Wervik",
    "province": "West-Vlaanderen",
    "name": "The Kringloopwinkel Menen",
    "category": "Thrift store",
    "address": "Kortrijkstraat 448, 8930 Menen, Belgium",
    "phone": "+32 56 23 29 40",
    "website": "dekringloopwinkel.be",
    "stars": "4.2",
    "review_count": "120 reviews",
    "google_maps_url": "https://www.google.com/maps/place/The+Kringloopwinkel+Menen/data=!4m7!3m6!1s0x47c32de621d31527:0x4c849bdadb0549f1!8m2!3d50.7996526!4d3.1397751!16s%2Fg%2F1tffhyd4!19sChIJJxXTIeYtw0cR8UkF29qbhEw?authuser=0&hl=en&rclk=1",
    "website_content": null
  },
  {
    "city": "Wervik",
    "province": "West-Vlaanderen",
    "name": "BROL - Friperie",
    "category": "Used clothing store",
    "address": "21A Rue de la République, 59560 Comines, France",
    "phone": "+33 7 61 75 30 34",
    "website": "facebook.com",
    "stars": "4.8",
    "review_count": "11 reviews",
    "google_maps_url": "https://www.google.com/maps/place/BROL+-+Friperie/data=!4m7!3m6!1s0x47dcd3f634d86131:0xe669ab9b3849c265!8m2!3d50.7639213!4d3.0048528!16s%2Fg%2F11x1q5wknp!19sChIJMWHYNPbT3EcRZcJJOJuraeY?authuser=0&hl=en&rclk=1",
    "website_content": null
  },
  {
    "city": "Wervik",
    "province": "West-Vlaanderen",
    "name": "Kringloopcentrum Zuid-West-Vlaanderen",
    "category": "Thrift store",
    "address": "Kortrijkstraat 448, 8930 Menen, Belgium",
    "phone": "+32 56 53 28 68",
    "website": "",
    "stars": "5.0",
    "review_count": "3 reviews",
    "google_maps_url": "https://www.google.com/maps/place/Kringloopcentrum+Zuid-West-Vlaanderen/data=!4m7!3m6!1s0x47c32e1f40bc8ed5:0xe26a70289168f24d!8m2!3d50.7993665!4d3.1401245!16s%2Fg%2F11bzx2vc9b!19sChIJ1Y68QB8uw0cRTfJokShwauI?authuser=0&hl=en&rclk=1",
    "website_content": null
  },
  {
    "city": "Wervik",
    "province": "West-Vlaanderen",
    "name": "Oxfam-Wereldwinkels",
    "category": "Store",
    "address": "Steenakker 19, 8940 Wervik, Belgium",
    "phone": "+32 473 29 35 62",
    "website": "",
    "stars": "4.5 stars · 2",
    "review_count": "Oxfam-Wereldwinkel Wevelgem VZW · 4.5 stars · 2 reviews · Association / Organization",
    "google_maps_url": "https://www.google.com/maps/place/Oxfam-Wereldwinkels/data=!4m7!3m6!1s0x47c32d1671c09833:0x40cf1d575142ce3b!8m2!3d50.7794589!4d3.0441082!16s%2Fg%2F11h64g5q8n!19sChIJM5jAcRYtw0cRO85CUVcdz0A?authuser=0&hl=en&rclk=1",
    "website_content": null
  },
  {
    "city": "Wervik",
    "province": "West-Vlaanderen",
    "name": "Eco-Shop Menen",
    "category": "Used furniture store",
    "address": "Waalvest 39, 8930 Menen, Belgium",
    "phone": "+32 56 20 17 83",
    "website": "ecoshop.be",
    "stars": "4.0",
    "review_count": "390 reviews",
    "google_maps_url": "https://www.google.com/maps/place/Eco-Shop+Menen/data=!4m7!3m6!1s0x47c32e0f77ea2937:0xa4a1d3c597e80cd3!8m2!3d50.7926202!4d3.1255956!16s%2Fg%2F1pxw36wlj!19sChIJNynqdw8uw0cR0wzol8XToaQ?authuser=0&hl=en&rclk=1",
    "website_content": null
  },
  {
    "city": "Wervik",
    "province": "West-Vlaanderen",
    "name": "resell cloths",
    "category": "Clothing store",
    "address": "Dadizelestraat 11, 8940 Wervik, Belgium",
    "phone": "+32 470 79 18 13",
    "website": "",
    "stars": null,
    "review_count": "Learn more about legal disclosure regarding public reviews on Google Maps",
    "google_maps_url": "https://www.google.com/maps/place/resell+cloths/data=!4m7!3m6!1s0x47c3332a7ce5445d:0x582f090b0fca83f0!8m2!3d50.8284481!4d3.086607!16s%2Fg%2F11xf1191_p!19sChIJXUTlfCozw0cR8IPKDwsJL1g?authuser=0&hl=en&rclk=1",
    "website_content": null
  },
  {
    "city": "Wervik",
    "province": "West-Vlaanderen",
    "name": "",
    "category": null,
    "address": "",
    "phone": "",
    "website": "",
    "stars": null,
    "review_count": null,
    "google_maps_url": "https://www.google.com/maps/place/De+Kringloopwinkel+Menen+-+Markt/data=!4m7!3m6!1s0x47c32f07d69c4ee7:0xe145cae02222a329!8m2!3d50.7957951!4d3.1215832!16s%2Fg%2F11p4bhyf0p!19sChIJ506c1gcvw0cRKaMiIuDKReE?authuser=0&hl=en&rclk=1",
    "website_content": null
  },
  {
    "city": "Wervik",
    "province": "West-Vlaanderen",
    "name": "De Kringloopwinkel Wevelgem",
    "category": "Thrift store",
    "address": "Menenstraat 308, 8560 Wevelgem, Belgium",
    "phone": "+32 56 23 29 40",
    "website": "dekringloopwinkel.be",
    "stars": "4.2",
    "review_count": "95 reviews",
    "google_maps_url": "https://www.google.com/maps/place/De+Kringloopwinkel+Wevelgem/data=!4m7!3m6!1s0x47c331d5998a9b05:0xf1a769415dc9d0b1!8m2!3d50.8037191!4d3.1613914!16s%2Fg%2F1vnnhk8c!19sChIJBZuKmdUxw0cRsdDJXUFpp_E?authuser=0&hl=en&rclk=1",
    "website_content": null
  }
]